{
  "project_info": {
    "project_number": "686162393508",
    "project_id": "yaripay",
    "storage_bucket": "yaripay.firebasestorage.app"
  },
  "client": [
    {
      "client_info": {
        "mobilesdk_app_id": "1:686162393508:android:0d4551f5a37339c7c06931",
        "android_client_info": {
          "package_name": "com.yaaripay"
        }
      },
      "oauth_client": [],
      "api_key": [
        {
          "current_key": "AIzaSyBuJX25H8mUXAI6pykneVqjoVCT7PTj_Z0"
        }
      ],
      "services": {
        "appinvite_service": {
          "other_platform_oauth_client": []
        }
      }
    }
  ],
  "configuration_version": "1"
}